{
    "name": "Castle Rush Unique",
    "civilization": "Spanish",
    "author": "Hera",
    "source": "https://buildorderguide.com",
    "description": "By hera 2024",
    "build_order": [
        {
            "villager_count": 6,
            "age": 1,
            "resources": {
                "wood": 0,
                "food": 6,
                "gold": 0,
                "stone": 0
            },
            "notes": [
                "6 - @animal/Sheep_aoe2DE.png@₆"
            ]
        },
        {
            "villager_count": 9,
            "age": 1,
            "resources": {
                "wood": 3,
                "food": 6,
                "gold": 0,
                "stone": 0
            },
            "notes": [
                "3 - @resource/Aoe2de_wood.png@₃"
            ]
        },
        {
            "villager_count": 10,
            "age": 1,
            "resources": {
                "wood": 3,
                "food": 7,
                "gold": 0,
                "stone": 0
            },
            "notes": [
                "1 - @animal/Boar_aoe2DE.png@₇"
            ]
        },
        {
            "villager_count": 11,
            "age": 1,
            "resources": {
                "wood": 3,
                "food": 8,
                "gold": 0,
                "stone": 0
            },
            "notes": [
                "1 - @resource/BerryBushDE.png@₈"
            ]
        },
        {
            "villager_count": 13,
            "age": 1,
            "resources": {
                "wood": 3,
                "food": 10,
                "gold": 0,
                "stone": 0
            },
            "notes": [
                "2 - @animal/Sheep_aoe2DE.png@₁₀"
            ]
        },
        {
            "villager_count": 17,
            "age": 1,
            "resources": {
                "wood": 3,
                "food": 14,
                "gold": 0,
                "stone": 0
            },
            "notes": [
                "4 - @resource/BerryBushDE.png@₅",
                "3@animal/Sheep_aoe2DE.png@₅ → @mill/FarmDE.png@₃"
            ]
        },
        {
            "villager_count": 22,
            "age": 1,
            "resources": {
                "wood": 8,
                "food": 14,
                "gold": 0,
                "stone": 0
            },
            "notes": [
                "5 - @resource/Aoe2de_wood.png@₈"
            ]
        },
        {
            "villager_count": 24,
            "age": 1,
            "resources": {
                "wood": 8,
                "food": 14,
                "gold": 2,
                "stone": 0
            },
            "notes": [
                "2 - @resource/Aoe2de_gold.png@₂",
                "@age/FeudalAgeIconDE_alpha.png@"
            ]
        },
        {
            "villager_count": 24,
            "age": 2,
            "resources": {
                "wood": 11,
                "food": 7,
                "gold": 2,
                "stone": 4
            },
            "notes": [
                "4@animal/Sheep_aoe2DE.png@₁₀ → @resource/Aoe2de_stone.png@₄",
                "3@animal/Sheep_aoe2DE.png@₇ → @resource/Aoe2de_wood.png@₁₁"
            ]
        },
        {
            "villager_count": 24,
            "age": 2,
            "resources": {
                "wood": 11,
                "food": 7,
                "gold": 2,
                "stone": 4
            },
            "notes": [
                "3@resource/Aoe2de_wood.png@₈ → @other/House_aoe2DE.png@@blacksmith/Blacksmith_aoe2de.png@@market/Market_aoe2DE.png@ → @resource/Aoe2de_wood.png@"
            ]
        },
        {
            "villager_count": 26,
            "age": 2,
            "resources": {
                "wood": 11,
                "food": 7,
                "gold": 2,
                "stone": 6
            },
            "notes": [
                "2 - @resource/Aoe2de_stone.png@₆",
                "@age/CastleAgeIconDE_alpha.png@"
            ]
        },
        {
            "villager_count": 26,
            "age": 3,
            "resources": {
                "wood": 11,
                "food": 7,
                "gold": 2,
                "stone": 6
            },
            "notes": [
                "@lumber_camp/DoubleBitAxe_aoe2DE.png@@mill/HorseCollarDE.png@"
            ]
        },
        {
            "villager_count": 26,
            "age": 3,
            "resources": {
                "wood": 11,
                "food": 7,
                "gold": 2,
                "stone": 6
            },
            "notes": [
                "@lumber_camp/BowSawDE.png@",
                "@resource/Aoe2de_hammer.png@ @castle/Castle_aoe2DE.png@"
            ]
        }
    ]
}
