{
    "name": "Fast Horse Francs4",
    "civilization": "Franks",
    "author": "Imperius-Tower",
    "source": "https://buildorderguide.com",
    "description": "Fast Feudal with 4 Scouts => Transition into Castle Age with 2 Stable Knights",
    "build_order": [
        {
            "age": 1,
            "villager_count": 7,
            "resources": {
                "wood": 0,
                "food": 7,
                "gold": 0,
                "stone": 0
            },
            "notes": [
                "@resource/Aoe2de_hammer.png@ (@other/House_aoe2DE.png@@other/House_aoe2DE.png@)",
                "7 - @animal/Sheep_aoe2DE.png@",
                "2 - @lumber_camp/Lumber_camp_aoe2de.png@",
                "1 - @animal/Boar_aoe2DE.png@ during 3rd @animal/Sheep_aoe2DE.png@"
            ]
        },
        {
            "age": 1,
            "villager_count": 18,
            "resources": {
                "wood": 2,
                "food": 16,
                "gold": 0,
                "stone": 0
            },
            "notes": [
                "1 - @animal/Sheep_aoe2DE.png@",
                "1 - @resource/Aoe2de_hammer.png@ (@other/House_aoe2DE.png@ @other/House_aoe2DE.png@+ @resource/BerryBushDE.png@ @mill/Mill_aoe2de.png@)",
                "3 - @animal/Sheep_aoe2DE.png@",
                "3 - @resource/BerryBushDE.png@"
            ]
        },
        {
            "age": 1,
            "villager_count": 18,
            "resources": {
                "wood": 7,
                "food": 11,
                "gold": 0,
                "stone": 0
            },
            "notes": [
                "5 @animal/Boar_aoe2DE.png@ → @resource/Aoe2de_wood.png@",
                "@town_center/LoomDE.png@",
                "@animal/Sheep_aoe2DE.png@ →  @resource/Aoe2de_wood.png@",
                "@age/FeudalAgeIconDE_alpha.png@"
            ]
        },
        {
            "age": 1,
            "villager_count": 18,
            "resources": {
                "wood": 10,
                "food": 4,
                "gold": 0,
                "stone": 0,
                "builder": 4
            },
            "notes": [
                "@resource/MaleVillDE_alpha.png@ - @resource/Aoe2de_gold.png@",	
"@resource/BerryBushDE.png@ -→ 4 @resource/Aoe2de_gold.png@",
"@resource/Aoe2de_wood.png@ → @resource/Aoe2de_hammer.png@ (@defensive_structures/Palisade_gate_aoe2DE.png@ + @other/House_aoe2DE.png@@other/House_aoe2DE.png@ + @defensive_structures/Palisade_wall_aoe2de.png@)",
"@resource/Aoe2de_wood.png@ → @resource/Aoe2de_hammer.png@ (@barracks/Barracks_aoe2DE.png@ + @other/House_aoe2DE.png@ + @stable/Stable_aoe2DE.png@ + )"

            ]
        },
        {
            "age": 2,
            "villager_count": 30,
            "resources": {
                "wood": 14,
                "food": 12,
                "gold": 4,
                "stone": 0
            },
            "notes": [
                "@lumber_camp/DoubleBitAxe_aoe2DE.png@",
                "2 ~ @stable/Scoutcavalry_aoe2DE.png@",
                "18 @mill/FarmDE.png@  @town_center/WheelbarrowDE.png@ @mill/FarmDE.png@",
                ""
            ]
        },
      {
            "age": 2,
            "villager_count": 36,
            "resources": {
                "wood": 14,
                "food": 12,
                "gold": 8,
                "stone": 0,
                "builder": 2
            },
            "notes": [
               "@resource/Aoe2de_hammer.png@(@blacksmith/Blacksmith_aoe2de.png@ + @market/Market_aoe2DE.png@ + @stable/Stable_aoe2DE.png@@stable/Stable_aoe2DE.png@ + @other/House_aoe2DE.png@@other/House_aoe2DE.png@)",
             "6- @resource/Aoe2de_gold.png@",
             "@age/CastleAgeIconDE_alpha.png@",
                "@resource/MaleVillDE_alpha.png@ - @resource/Aoe2de_stone.png@"
            ]
        },
      {
            "age": 2,
            "villager_count": 36,
            "resources": {
                "wood": 14,
                "food": 12,
                "gold": 6,
                "stone": 0,
                "builder": 2
            },
            "notes": [               
                
              "@blacksmith/ScaleBardingArmorDE.png@ + @blacksmith/Forging_aoe2de.png@ + @blacksmith/FletchingDE.png@",
             "@mining_camp/GoldMiningDE.png@ + @mining_camp/StoneMiningDE.png@",
             "@resource/Aoe2de_hammer.png@ (@defensive_structures/Palisade_wall_aoe2de.png@ @icon/top_arrow.png@@monastery/SanctityDE.png@)"
            ]
        },
      {
            "age": 3,
            "villager_count": 40,
            "resources": {
                "wood": 14,
                "food": 12,
                "gold": 8,
                "stone": 4
            },
            "notes": [
                "@stable/Knight_aoe2DE.png@",
                "@lumber_camp/BowSawDE.png@ + @mining_camp/GoldShaftMiningDE.png@",
                "@blacksmith/ChainBardingDE.png@ + @blacksmith/IronCastingDE.png@ + @stable/HusbandryDE.png@"
            ]
        },
      {
            "age": 3,
            "villager_count": 40,
            "resources": {
                "wood": 14,
                "food": 12,
                "gold": 8,
                "stone": 4
            },
            "notes": [
                "@resource/Aoe2de_stone.png@ → @town_center/Towncenter_aoe2DE.png@@resource/Aoe2de_wood.png@",
                "10 - @town_center/Towncenter_aoe2DE.png@@mill/FarmDE.png@",
                "monastery/MonasteryAoe2DE.png@  (3@monastery/Monk_aoe2DE.png@@monastery/SanctityDE.png@)",
                "monastery/MonasteryAoe2DE.png@ @university/University_AoE2_DE.png@"
            ]
        },
{
            "age": 3,
            "villager_count": 40,
            "resources": {
                "wood": 14,
                "food": 12,
                "gold": 8,
                "stone": 4
            },
            "notes": [
                "@castle/Castle_aoe2DE.png@ (@unique_unit/ThrowingAxemanIcon-DE.png@@blacksmith/ScaleMailArmorDE.png@@blacksmith/ChainMailArmorDE.png@)",
                "5@barracks/Barracks_aoe2DE.png@(@barracks/Halberdier_aoe2DE.png@@barracks/Champion_aoe2DE.png@)"
            ]
        },
{
            "age": 4,
            "villager_count": 40,
            "resources": {
                "wood": 14,
                "food": 12,
                "gold": 8,
                "stone": 4
            },
            "notes": [
                "@age/ImperialAgeIconDE_alpha.png@  @university/ChemistryDE.png@ @university/SiegeEngineersDE.png@ @siege_workshop/Bombard_cannon_aoe2DE.png@",
                "@barracks/Barracks_aoe2DE.png@(@barracks/Champion_aoe2DE.png@)",
                ""
            ]
        }
    ]
}