{
    "name": "RiseofRawrm6",
    "civilization": "Generic",
    "author": "Tower",
    "source": "Tower",
    "description": "MAA into Scorp into Cent",
    "build_order": [
        {
            "age": 1,
            "villager_count": 24,
            "resources": {
                "wood": 8,
                "food": 16,
                "gold": 0,
                "stone": 0
            },
            "notes": [
                "6 - @animal/Sheep_aoe2DE.png@₆",
                "1 - @animal/Boar_aoe2DE.png@₇",
                "4 - @lumber_camp/Lumber_camp_aoe2de.png@₄ (@other/House_aoe2DE.png@)",
                "4 - @mill/Mill_aoe2de.png@ @resource/BerryBushDE.png@₄",
                "5 - @animal/Sheep_aoe2DE.png@₁₂ (@other/House_aoe2DE.png@)",
                "4 - @resource/Aoe2de_wood.png@₈"
            ]
        },
        {
            "age": 1,
            "villager_count": 24,
            "resources": {
                "wood": 16,
                "food": 4,
                "gold": 4,
                "stone": 0
            },
            "notes": [
                "8@animal/Sheep_aoe2DE.png@₄ → @lumber_camp/Lumber_camp_aoe2de.png@₁₆",
                "4@animal/Sheep_aoe2DE.png@₀ → @mining_camp/Mining_camp_aoe2de.png@@resource/Aoe2de_gold.png@₄",
                "@town_center/LoomDE.png@ @age/FeudalAgeIconDE_alpha.png@₂₄"
            ]
        },
        {
            "age": 2,
            "villager_count": 42,
            "resources": {
                "wood": 16,
                "food": 18,
                "gold": 8,
                "stone": 0
            },
            "notes": [
                "2@resource/BerryBushDE.png@₂ → @other/House_aoe2DE.png@@blacksmith/Blacksmith_aoe2de.png@@market/Market_aoe2DE.png@@other/House_aoe2DE.png@@defensive_structures/Palisade_wall_aoe2de.png@ → @resource/BerryBushDE.png@₄",
                "@lumber_camp/DoubleBitAxe_aoe2DE.png@@mill/HorseCollarDE.png@",
                "18 - @mill/FarmDE.png@₁₈",
                "4@resource/BerryBushDE.png@₀ → @resource/Aoe2de_gold.png@₈"
            ]
        },
        {
            "age": 2,
            "villager_count": 42,
            "resources": {
                "wood": 16,
                "food": 18,
                "gold": 8,
                "stone": 0
            },
            "notes": [
                "@age/CastleAgeIconDE_alpha.png@@town_center/WheelbarrowDE.png@",
                "@mining_camp/GoldMiningDE.png@@mining_camp/StoneMiningDE.png@",
                "→ @resource/Aoe2de_gold.png@"
            ]
        },
        {
            "age": 3,
            "villager_count": 42,
            "resources": {
                "wood": 16,
                "food": 18,
                "gold": 8,
                "stone": 0
            },
            "notes": [
                "@siege_workshop/Siege_workshop_aoe2DE.png@@siege_workshop/Siege_workshop_aoe2DE.png@@siege_workshop/Scorpion_aoe2DE.png@",
                "@university/University_AoE2_DE.png@@university/BallisticsDE.png@",
                "@lumber_camp/BowSawDE.png@@mill/HeavyPlowDE.png@@town_center/HandcartDE.png@",
                "@monastery/MonasteryAoe2DE.png@@monastery/Monk_aoe2DE.png@"
            ]
        },
        {
            "age": 3,
            "villager_count": 42,
            "resources": {
                "wood": 16,
                "food": 18,
                "gold": 8,
                "stone": 0
            },
            "notes": [
                "@town_center/Towncenter_aoe2DE.png@ @resource/Aoe2de_gold.png@@resource/Aoe2de_gold.png@@town_center/Towncenter_aoe2DE.png@ @resource/Aoe2de_stone.png@",
                "@castle/Castle_aoe2DE.png@@mining_camp/Mining_camp_aoe2de.png@",
                "5@barracks/Barracks_aoe2DE.png@",
                "∞ @siege_workshop/Scorpion_aoe2DE.png@@barracks/Longswordsman_aoe2DE.png@@barracks/Aoe2-infantry-2-pikeman.png@"
            ]
        }
    ]
}